wirestack/__init__.py
wirestack/app.py
wirestack/manager.py
wirestack-0.1.0.dist-info/LICENSE
wirestack-0.1.0.dist-info/WHEEL
wirestack-0.1.0.dist-info/METADATA
wirestack-0.1.0.dist-info/RECORD
